radical.entk-1.5.12-py3.9-nspkg.pth
radical/entk/SDIST
radical/entk/VERSION
radical/entk/__init__.py
radical/entk/constants.py
radical/entk/exceptions.py
radical/entk/pipeline.py
radical/entk/radical.entk-1.5.12-v1.5.12-HEAD-detached-at-v1.5.12.tar.gz
radical/entk/stage.py
radical/entk/states.py
radical/entk/task.py
radical/entk/appman/__init__.py
radical/entk/appman/appmanager.py
radical/entk/appman/config.json
radical/entk/appman/wfprocessor.py
radical/entk/execman/__init__.py
radical/entk/execman/base/__init__.py
radical/entk/execman/base/resource_manager.py
radical/entk/execman/base/task_manager.py
radical/entk/execman/mock/__init__.py
radical/entk/execman/mock/resource_manager.py
radical/entk/execman/mock/task_manager.py
radical/entk/execman/rp/__init__.py
radical/entk/execman/rp/resource_manager.py
radical/entk/execman/rp/task_manager.py
radical/entk/execman/rp/task_processor.py
radical/entk/utils/__init__.py
radical/entk/utils/prof_utils.py
radical.entk-1.5.12.data/data/share/radical.entk/examples/advanced/adapt_ta.py
radical.entk-1.5.12.data/data/share/radical.entk/examples/advanced/adapt_tc.py
radical.entk-1.5.12.data/data/share/radical.entk/examples/advanced/adapt_to.py
radical.entk-1.5.12.data/data/share/radical.entk/examples/analytics/get_durations.py
radical.entk-1.5.12.data/data/share/radical.entk/examples/analytics/get_timestamps.py
radical.entk-1.5.12.data/data/share/radical.entk/examples/simple/eop.py
radical.entk-1.5.12.data/data/share/radical.entk/examples/simple/poe.py
radical.entk-1.5.12.data/data/share/radical.entk/examples/simple/sow.py
radical.entk-1.5.12.data/data/share/radical.entk/examples/user_guide/add_data.py
radical.entk-1.5.12.data/data/share/radical.entk/examples/user_guide/add_pipelines.py
radical.entk-1.5.12.data/data/share/radical.entk/examples/user_guide/add_shared_data.py
radical.entk-1.5.12.data/data/share/radical.entk/examples/user_guide/add_stages.py
radical.entk-1.5.12.dist-info/LICENSE.md
radical.entk-1.5.12.dist-info/METADATA
radical.entk-1.5.12.dist-info/WHEEL
radical.entk-1.5.12.dist-info/namespace_packages.txt
radical.entk-1.5.12.dist-info/top_level.txt
radical.entk-1.5.12.dist-info/RECORD
