Metadata-Version: 2.1
Name: radical.entk
Version: 1.5.12
Summary: Radical Ensemble Toolkit.
Home-page: https://www.github.com/radical-cybertools/radical.entk/
Author: RADICAL Group at Rutgers University
Author-email: radical@rutgers.edu
Maintainer: The RADICAL Group
Maintainer-email: radical@rutgers.edu
License: MIT
Keywords: ensemble workflow execution
Platform: UNKNOWN
Classifier: Development Status :: 5 - Production/Stable
Classifier: Intended Audience :: Developers
Classifier: Environment :: Console
Classifier: License :: OSI Approved :: MIT License
Classifier: Programming Language :: Python
Classifier: Programming Language :: Python :: 3
Classifier: Programming Language :: Python :: 3.6
Classifier: Topic :: Utilities
Classifier: Topic :: System :: Distributed Computing
Classifier: Topic :: Scientific/Engineering
Classifier: Operating System :: MacOS :: MacOS X
Classifier: Operating System :: POSIX
Classifier: Operating System :: Unix
Requires-Dist: radical.utils
Requires-Dist: radical.pilot
Requires-Dist: pika (==0.13.0)
Requires-Dist: sphinx
